actuapy/__init__.py
actuapy/core.py
actuapy/helper.py
actuapy/util.py
actuapy-0.0.3.dist-info/LICENSE
actuapy-0.0.3.dist-info/METADATA
actuapy-0.0.3.dist-info/WHEEL
actuapy-0.0.3.dist-info/top_level.txt
actuapy-0.0.3.dist-info/RECORD
