Metadata-Version: 2.1
Name: actuapy
Version: 0.0.3
Summary: useful snippets for actuaries
Home-page: https://github.com/ayanamizuta/actuary
Author: Rei Mizuta
Author-email: ayanamizuta832@gmail.com
License: MIT License
Requires-Dist: matplotlib (==3.1.1)
Requires-Dist: pandas (==0.23.0)
Requires-Dist: numpy (==1.17.0)
